pyroll/basic.py
pyroll_basic-3.1.0.dist-info/METADATA
pyroll_basic-3.1.0.dist-info/WHEEL
pyroll_basic-3.1.0.dist-info/licenses/LICENSE
pyroll_basic-3.1.0.dist-info/RECORD
