Metadata-Version: 2.4
Name: pyroll-basic
Version: 3.1.0
Summary: A meta package for installing quickly the PyRolL core and a set of basic plugins and extensions.
Project-URL: Homepage, https://pyroll.readthedocs.io
Project-URL: Repository, https://github.com/pyroll-project/pyroll-basic
Author-email: Christoph Renzing <christoph.renzing@imf.tu-freiberg.de>, Max Weiner <max.weiner@imf.tu-freiberg.de>
License-Expression: BSD-3-Clause
License-File: LICENSE
Classifier: Development Status :: 5 - Production/Stable
Classifier: Framework :: Hatch
Classifier: Framework :: IPython
Classifier: Framework :: Jupyter
Classifier: Framework :: Pytest
Classifier: Framework :: Sphinx
Classifier: Intended Audience :: Manufacturing
Classifier: Intended Audience :: Science/Research
Classifier: License :: OSI Approved :: BSD License
Classifier: Natural Language :: English
Classifier: Operating System :: OS Independent
Classifier: Programming Language :: Python :: 3
Classifier: Programming Language :: Python :: 3.9
Classifier: Programming Language :: Python :: 3.10
Classifier: Programming Language :: Python :: 3.11
Classifier: Topic :: Scientific/Engineering
Requires-Python: >=3.9
Requires-Dist: plotly
Requires-Dist: pyroll-cli~=3.0
Requires-Dist: pyroll-core~=3.1
Requires-Dist: pyroll-elastic-mill-spring~=3.0
Requires-Dist: pyroll-export~=3.0
Requires-Dist: pyroll-freiberg-flow-stress~=3.0
Requires-Dist: pyroll-gripping-analysis~=3.0
Requires-Dist: pyroll-integral-thermal~=3.0
Requires-Dist: pyroll-interface-friction~=3.0
Requires-Dist: pyroll-lendl-equivalent-method~=3.0
Requires-Dist: pyroll-linear-thermal-expansion~=3.0
Requires-Dist: pyroll-lippmann-mahrenholz-force-torque~=3.0
Requires-Dist: pyroll-report~=3.1
Requires-Dist: pyroll-wusatowski-spreading~=3.0
Requires-Dist: pyroll-zouhar-contact~=3.0
